keviusdb/__init__.py
keviusdb/comparison/__init__.py
keviusdb/core/__init__.py
keviusdb/interfaces/__init__.py
keviusdb/iteration/__init__.py
keviusdb/memory/__init__.py
keviusdb/memory/agent_memory.py
keviusdb/memory/retrieval.py
keviusdb/memory/session.py
keviusdb/memory/types.py
keviusdb/memory/utils.py
keviusdb/storage/__init__.py
keviusdb/transaction/__init__.py
tests/__init__.py
tests/test_keviusdb.py
tests/test_memory.py
keviusdb-1.1.0.dist-info/LICENSE.md
keviusdb-1.1.0.dist-info/METADATA
keviusdb-1.1.0.dist-info/WHEEL
keviusdb-1.1.0.dist-info/top_level.txt
keviusdb-1.1.0.dist-info/RECORD
